textColor/__init__.py
textcolor-3.1.0.dist-info/METADATA
textcolor-3.1.0.dist-info/WHEEL
textcolor-3.1.0.dist-info/licenses/LICENSE
textcolor-3.1.0.dist-info/RECORD
