Metadata-Version: 2.1
Name: textColor
Version: 3.1.0
Summary: This is an easy to use Python library which allows you to make your terminal outputs more colorful and therefore easier to read and understand 
Project-URL: Homepage, https://github.com/jramrath/textColor
Project-URL: Bug Tracker, https://github.com/jramrath/textColor/issues
Author-email: Jannik Ramrath <jannik@ramrath.me>
License-File: LICENSE
Classifier: License :: OSI Approved :: GNU General Public License v3 (GPLv3)
Classifier: Operating System :: OS Independent
Classifier: Programming Language :: Python :: 3
Requires-Python: >=3.7
